jrlogo/__init__.py
jrlogo/color.py
jrlogo/console.py
jrlogo/screen.py
jrlogo/shape.py
jrlogo/turtle.py
jrlogo-0.0.3.dist-info/LICENSE
jrlogo-0.0.3.dist-info/METADATA
jrlogo-0.0.3.dist-info/WHEEL
jrlogo-0.0.3.dist-info/top_level.txt
jrlogo-0.0.3.dist-info/RECORD
