Metadata-Version: 2.1
Name: jrlogo
Version: 0.0.3
Summary: A package for Jieer Edu to teach pc-logo and python
Home-page: https://github.com/klarkxy/jieer-logo
Author: klarkxy
Author-email: 278370456@qq.com
License: SATA
Platform: UNKNOWN
